<?xml version="1.0" encoding="UTF-8"?>
<caaml:SnowProfile xmlns:caaml="http://caaml.org/Schemas/SnowProfileIACS/v6.0.3" xmlns:gml="http://www.opengis.net/gml" xmlns:snowpilot="http://www.snowpilot.org/Schemas/caaml" gml:id="SnowPilot-6537">
  <caaml:metaData/>
  <caaml:timeRef>
    <caaml:recordTime>
      <caaml:TimeInstant>
        <caaml:timePosition>2018-01-23T16:00:00</caaml:timePosition>
      </caaml:TimeInstant>
    </caaml:recordTime>
    <caaml:dateTimeReport>2018-02-07T13:35:52-09:00</caaml:dateTimeReport>
    <caaml:dateTimeLastEdit>2026-02-08T13:50:38-09:00</caaml:dateTimeLastEdit>
  </caaml:timeRef>
  <caaml:srcRef>
    <caaml:Person gml:id="SnowPilot-User-4829">
      <caaml:name>Dogarf</caaml:name>
    </caaml:Person>
  </caaml:srcRef>
  <caaml:locRef gml:id="location-nid-6537">
    <caaml:name>bench Below Oliver</caaml:name>
    <caaml:obsPointSubType>SnowPilot Snowpit site</caaml:obsPointSubType>
    <caaml:validElevation>
      <caaml:ElevationPosition uom="m">
        <caaml:position>2554</caaml:position>
      </caaml:ElevationPosition>
    </caaml:validElevation>
    <caaml:validAspect>
      <caaml:AspectPosition>
        <caaml:position>N</caaml:position>
      </caaml:AspectPosition>
    </caaml:validAspect>
    <caaml:validSlopeAngle>
      <caaml:SlopeAnglePosition uom="deg">
        <caaml:position>24</caaml:position>
      </caaml:SlopeAnglePosition>
    </caaml:validSlopeAngle>
    <caaml:country>US</caaml:country>
    <caaml:region>WY</caaml:region>
  </caaml:locRef>
  <caaml:snowProfileResultsOf>
    <caaml:SnowProfileMeasurements dir="top down">
      <caaml:metaData/>
      <caaml:profileDepth uom="cm">200</caaml:profileDepth>
      <caaml:weatherCond>
        <caaml:skyCond>OVC</caaml:skyCond>
        <caaml:windSpd uom="">L</caaml:windSpd>
      </caaml:weatherCond>
      <caaml:snowPackCond>
        <caaml:hS>
          <caaml:Components>
            <caaml:height uom="cm">200</caaml:height>
          </caaml:Components>
        </caaml:hS>
      </caaml:snowPackCond>
      <caaml:surfCond>
        <caaml:metaData/>
        <caaml:customData/>
      </caaml:surfCond>
      <caaml:stratProfile>
        <caaml:stratMetaData/>
        <caaml:Layer>
          <caaml:depthTop uom="cm">0</caaml:depthTop>
          <caaml:thickness uom="cm">30</caaml:thickness>
          <caaml:grainFormPrimary>PPsd</caaml:grainFormPrimary>
          <caaml:hardnessTop uom="">F</caaml:hardnessTop>
          <caaml:hardnessBottom uom="">F</caaml:hardnessBottom>
        </caaml:Layer>
        <caaml:Layer>
          <caaml:depthTop uom="cm">30</caaml:depthTop>
          <caaml:thickness uom="cm">5</caaml:thickness>
          <caaml:grainFormPrimary>SHsu</caaml:grainFormPrimary>
          <caaml:hardness uom="">4F</caaml:hardness>
        </caaml:Layer>
        <caaml:Layer>
          <caaml:depthTop uom="cm">35</caaml:depthTop>
          <caaml:thickness uom="cm">25</caaml:thickness>
          <caaml:grainFormPrimary>FCxr</caaml:grainFormPrimary>
          <caaml:hardness uom="">4F</caaml:hardness>
        </caaml:Layer>
        <caaml:Layer>
          <caaml:depthTop uom="cm">60</caaml:depthTop>
          <caaml:thickness uom="cm">6</caaml:thickness>
          <caaml:grainFormPrimary>FCxr</caaml:grainFormPrimary>
          <caaml:hardness uom="">1F</caaml:hardness>
        </caaml:Layer>
        <caaml:Layer>
          <caaml:depthTop uom="cm">66</caaml:depthTop>
          <caaml:thickness uom="cm">4</caaml:thickness>
          <caaml:grainFormPrimary>PPgp</caaml:grainFormPrimary>
          <caaml:hardness uom="">1F</caaml:hardness>
        </caaml:Layer>
        <caaml:Layer>
          <caaml:depthTop uom="cm">70</caaml:depthTop>
          <caaml:thickness uom="cm">10</caaml:thickness>
          <caaml:grainFormPrimary>FCxr</caaml:grainFormPrimary>
          <caaml:hardness uom="">1F</caaml:hardness>
        </caaml:Layer>
        <caaml:Layer>
          <caaml:depthTop uom="cm">80</caaml:depthTop>
          <caaml:thickness uom="cm">2</caaml:thickness>
          <caaml:grainFormPrimary>MFcr</caaml:grainFormPrimary>
          <caaml:hardness uom="">P</caaml:hardness>
        </caaml:Layer>
        <caaml:Layer>
          <caaml:depthTop uom="cm">82</caaml:depthTop>
          <caaml:thickness uom="cm">48</caaml:thickness>
          <caaml:grainFormPrimary>FCxr</caaml:grainFormPrimary>
          <caaml:hardness uom="">1F</caaml:hardness>
        </caaml:Layer>
        <caaml:Layer>
          <caaml:depthTop uom="cm">130</caaml:depthTop>
          <caaml:thickness uom="cm">5</caaml:thickness>
          <caaml:grainFormPrimary>MFcr</caaml:grainFormPrimary>
          <caaml:hardness uom="">P</caaml:hardness>
        </caaml:Layer>
        <caaml:Layer>
          <caaml:depthTop uom="cm">135</caaml:depthTop>
          <caaml:thickness uom="cm">10</caaml:thickness>
          <caaml:grainFormPrimary>FCso</caaml:grainFormPrimary>
          <caaml:hardness uom="">1F</caaml:hardness>
          <caaml:layerOfConcern>true</caaml:layerOfConcern>
        </caaml:Layer>
        <caaml:Layer>
          <caaml:depthTop uom="cm">145</caaml:depthTop>
          <caaml:thickness uom="cm">5</caaml:thickness>
          <caaml:grainFormPrimary>MFcr</caaml:grainFormPrimary>
          <caaml:hardnessTop uom="">P</caaml:hardnessTop>
          <caaml:hardnessBottom uom="">P</caaml:hardnessBottom>
        </caaml:Layer>
        <caaml:Layer>
          <caaml:depthTop uom="cm">150</caaml:depthTop>
          <caaml:thickness uom="cm">10</caaml:thickness>
          <caaml:grainFormPrimary>FCxr</caaml:grainFormPrimary>
          <caaml:hardness uom="">1F</caaml:hardness>
        </caaml:Layer>
        <caaml:Layer>
          <caaml:depthTop uom="cm">160</caaml:depthTop>
          <caaml:thickness uom="cm">40</caaml:thickness>
          <caaml:grainFormPrimary>MFcl</caaml:grainFormPrimary>
          <caaml:hardness uom="">P</caaml:hardness>
        </caaml:Layer>
      </caaml:stratProfile>
      <caaml:stbTests>
        <caaml:ComprTest>
          <caaml:failedOn>
            <caaml:Layer>
              <caaml:depthTop uom="cm">32</caaml:depthTop>
            </caaml:Layer>
            <caaml:Results>
              <caaml:fractureCharacter>SP</caaml:fractureCharacter>
              <caaml:testScore>4</caaml:testScore>
            </caaml:Results>
          </caaml:failedOn>
        </caaml:ComprTest>
        <caaml:ExtColumnTest>
          <caaml:noFailure/>
        </caaml:ExtColumnTest>
      </caaml:stbTests>
    </caaml:SnowProfileMeasurements>
  </caaml:snowProfileResultsOf>
  <caaml:application>SnowPilot</caaml:application>
  <caaml:applicationVersion>7.103-0.1</caaml:applicationVersion>
  <caaml:customData>
    <snowpilot:visibility>hidden</snowpilot:visibility>
  </caaml:customData>
</caaml:SnowProfile>
